[{"abbr":"wjq","id":440203,"name":"武江区","parentId":440200},{"abbr":"zjq","id":440204,"name":"浈江区","parentId":440200},{"abbr":"qjq","id":440205,"name":"曲江区","parentId":440200},{"abbr":"sxx","id":440222,"name":"始兴县","parentId":440200},{"abbr":"rhx","id":440224,"name":"仁化县","parentId":440200},{"abbr":"wyx","id":440229,"name":"翁源县","parentId":440200},{"abbr":"ryyzzzx","id":440232,"name":"乳源瑶族自治县","parentId":440200},{"abbr":"xfx","id":440233,"name":"新丰县","parentId":440200},{"abbr":"lcs","id":440281,"name":"乐昌市","parentId":440200},{"abbr":"nxs","id":440282,"name":"南雄市","parentId":440200}]